queueService/__init__.py
queueService/queueService.py
mqueueservice-0.0.2.dist-info/METADATA
mqueueservice-0.0.2.dist-info/WHEEL
mqueueservice-0.0.2.dist-info/top_level.txt
mqueueservice-0.0.2.dist-info/RECORD
