Metadata-Version: 2.1
Name: mqueueservice
Version: 0.0.2
Summary: A free queue service using ActiveMQ
Home-page: https://github.com/Soniyasharma6868/activeMqServices
Author: Soniya Sharma
Author-email: sharmasoniya6868@email.com
License: MIT
Project-URL: Source, https://github.com/Soniyasharma6868/activeMqServices
Platform: UNKNOWN
Classifier: Intended Audience :: Developers
Classifier: Topic :: Utilities
Classifier: License :: OSI Approved :: MIT License
Classifier: Programming Language :: Python :: 3
Requires-Python: >=3
Requires-Dist: stomp.py
